README
logo.png
setup-distutils.py
setup.py
compactxml/__init__.py
compactxml/compact.py
compactxml/error.py
compactxml/expand.py
compactxml/expression.py
compactxml/grammar-with-debug.py
compactxml/grammar.py
compactxml/macro.py
compactxml/namespace.py
compactxml/parser.py
compactxml/pyparsingaddons.py
compactxml/resolve.py
compactxml/variable.py
compactxml.egg-info/PKG-INFO
compactxml.egg-info/SOURCES.txt
compactxml.egg-info/dependency_links.txt
compactxml.egg-info/requires.txt
compactxml.egg-info/top_level.txt
compactxml/tests/__init__.py
compactxml/tests/api_test.py
compactxml/tests/compact_test.py
compactxml/tests/expand_test.py
compactxml/tests/resolve_test.py
compactxml/tests/speed_test.py
dist/compactxml-2.0.0-py2.6.egg
dist/compactxml-2.0.0.tar.gz
dist/compactxml-2.0.1-1.noarch.rpm
dist/compactxml-2.0.1-1.src.rpm
dist/compactxml-2.0.1-py2.6.egg
dist/compactxml-2.0.1.tar.gz
dist/compactxml-2.0.1.zip
dist/compactxml-2.0.2-1.noarch.rpm
dist/compactxml-2.0.2-1.src.rpm
dist/compactxml-2.0.2-py2.6.egg
dist/compactxml-2.0.2.tar.gz
dist/compactxml-2.0.2.zip
dist/compactxml-2.0.3-1.noarch.rpm
dist/compactxml-2.0.3-1.src.rpm
dist/compactxml-2.0.3-py2.6.egg
dist/compactxml-2.0.3.tar.gz
dist/compactxml-2.0.3.zip
dist/compactxml-2.0.4-py2.6.egg
dist/compactxml-2.0.4.linux-x86_64.tar.gz
dist/compactxml-2.0.4.tar.gz
dist/compactxml-2.0.5-py2.6.egg
dist/compactxml-2.0.5.linux-x86_64.tar.gz
dist/compactxml-2.0.5.tar.gz
dist/compactxml-2.0.5.zip
dist/compactxml-2.1.0-py2.7.egg
dist/compactxml-2.1.0.tar.gz
dist/compactxml-2.1.0.zip
docs/compact.rst
docs/compactxml.vim
docs/gizmo.rst
docs/google.wiki
docs/grammar.txt
docs/sample.cxml
docs/HTML/index.html
scripts/compactxml