Metadata-Version: 1.0
Name: compactxml
Version: 2.1.0
Summary: Parser and converter for an alternate compact XML syntax.
Home-page: http://code.google.com/p/compactxml/
Author: John Krukoff
Author-email: python@cultist.org
License: GPL v2
Download-URL: http://code.google.com/p/compactxml/downloads/list
Keywords: xml compact shorter format
Platform: UNKNOWN
